viroconcom/__init__.py
viroconcom/_n_sphere.py
viroconcom/conftest.py
viroconcom/contour_analysis.py
viroconcom/contours.py
viroconcom/distributions.py
viroconcom/fitting.py
viroconcom/params.py
viroconcom/plot.py
viroconcom/read_write.py
viroconcom/settings.py
viroconcom/utility.py
viroconcom/version.py
viroconcom-1.4.14.dist-info/LICENSE
viroconcom-1.4.14.dist-info/METADATA
viroconcom-1.4.14.dist-info/WHEEL
viroconcom-1.4.14.dist-info/top_level.txt
viroconcom-1.4.14.dist-info/RECORD
