Metadata-Version: 2.1
Name: viroconcom
Version: 1.4.14
Summary: ViroCon is a software to compute environmental contour
Home-page: https://github.com/virocon-organization/viroconcom
Author: ViroCon Team
Author-email: virocon@uni-bremen.de
License: UNKNOWN
Download-URL: https://github.com/virocon-organization/viroconcom/archive/1.4.14.tar.gz
Project-URL: Documentation, https://virocon-organization.github.io/viroconcom/
Project-URL: Source Code, https://github.com/virocon-organization/viroconcom
Platform: UNKNOWN
Classifier: Development Status :: 5 - Production/Stable
Classifier: Intended Audience :: Science/Research
Classifier: Topic :: Scientific/Engineering
Classifier: License :: OSI Approved :: MIT License
Classifier: Programming Language :: Python :: 3.8
Requires-Dist: matplotlib (>=2.2.0networkx)
Requires-Dist: numpy
Requires-Dist: pandas
Requires-Dist: scikit-learn
Requires-Dist: scipy
Requires-Dist: statsmodels
Provides-Extra: dev
Requires-Dist: Sphinx ; extra == 'dev'
Provides-Extra: test
Requires-Dist: pytest ; extra == 'test'
Requires-Dist: pytest-cov ; extra == 'test'
Requires-Dist: coverage ; extra == 'test'
Requires-Dist: coveralls ; extra == 'test'
